weatherbit/__init__.py
weatherbit/api.py
weatherbit/models.py
weatherbit/utils.py
pyweatherbit-2.2.2.dist-info/LICENSE
pyweatherbit-2.2.2.dist-info/METADATA
pyweatherbit-2.2.2.dist-info/WHEEL
pyweatherbit-2.2.2.dist-info/top_level.txt
pyweatherbit-2.2.2.dist-info/RECORD
