Metadata-Version: 2.1
Name: pyweatherbit
Version: 2.2.2
Summary: A python weather api wrapper for the Weatherbit.io API.
Home-page: http://www.weatherbit.io
Author: Colin Craig
Author-email: Colin Craig <colin@weatherbit.io>
License: MIT License
Project-URL: Homepage, https://github.com/weatherbit/weatherbit-python
Project-URL: Bug Tracker, https://github.com/weatherbit/weatherbit-python/issues
Keywords: weather,API,python,wrapper,weatherbit
Classifier: Programming Language :: Python :: 3
Classifier: Operating System :: OS Independent
Requires-Python: >=3.7
License-File: LICENSE
